dbt/adapters/trino/__init__.py
dbt/adapters/trino/__version__.py
dbt/adapters/trino/column.py
dbt/adapters/trino/connections.py
dbt/adapters/trino/constants.py
dbt/adapters/trino/impl.py
dbt/adapters/trino/parse_model.py
dbt/adapters/trino/relation.py
dbt/adapters/trino/catalogs/__init__.py
dbt/adapters/trino/catalogs/_relation.py
dbt/adapters/trino/catalogs/_trino_catalog_metastore.py
dbt/include/trino/__init__.py
dbt/include/trino/dbt_project.yml
dbt/include/trino/sample_profiles.yml
dbt/include/trino/macros/adapters.sql
dbt/include/trino/macros/apply_grants.sql
dbt/include/trino/macros/catalog.sql
dbt/include/trino/macros/materializations/incremental.sql
dbt/include/trino/macros/materializations/materialized_view.sql
dbt/include/trino/macros/materializations/snapshot.sql
dbt/include/trino/macros/materializations/table.sql
dbt/include/trino/macros/materializations/view.sql
dbt/include/trino/macros/materializations/seeds/helpers.sql
dbt/include/trino/macros/utils/any_value.sql
dbt/include/trino/macros/utils/array_append.sql
dbt/include/trino/macros/utils/array_concat.sql
dbt/include/trino/macros/utils/array_construct.sql
dbt/include/trino/macros/utils/bool_or.sql
dbt/include/trino/macros/utils/datatypes.sql
dbt/include/trino/macros/utils/date_spine.sql
dbt/include/trino/macros/utils/date_trunc.sql
dbt/include/trino/macros/utils/dateadd.sql
dbt/include/trino/macros/utils/datediff.sql
dbt/include/trino/macros/utils/hash.sql
dbt/include/trino/macros/utils/listagg.sql
dbt/include/trino/macros/utils/right.sql
dbt/include/trino/macros/utils/safe_cast.sql
dbt/include/trino/macros/utils/split_part.sql
dbt/include/trino/macros/utils/timestamps.sql
dbt_trino-1.10.0.dist-info/licenses/LICENSE.txt
dbt_trino-1.10.0.dist-info/METADATA
dbt_trino-1.10.0.dist-info/WHEEL
dbt_trino-1.10.0.dist-info/top_level.txt
dbt_trino-1.10.0.dist-info/RECORD
