Metadata-Version: 2.4
Name: dbt-trino
Version: 1.10.0
Summary: The trino adapter plugin for dbt (data build tool)
Home-page: https://github.com/starburstdata/dbt-trino
Author: Starburst Data
Author-email: info@starburstdata.com
License: Apache License 2.0
Platform: any
Classifier: Development Status :: 5 - Production/Stable
Classifier: License :: OSI Approved :: Apache Software License
Classifier: Operating System :: Microsoft :: Windows
Classifier: Operating System :: MacOS :: MacOS X
Classifier: Operating System :: POSIX :: Linux
Classifier: Programming Language :: Python :: 3.9
Classifier: Programming Language :: Python :: 3.10
Classifier: Programming Language :: Python :: 3.11
Classifier: Programming Language :: Python :: 3.12
Classifier: Programming Language :: Python :: 3.13
Requires-Python: >=3.9
License-File: LICENSE.txt
Requires-Dist: dbt-common<2.0,>=1.25.0
Requires-Dist: dbt-adapters<1.17,>=1.15.1
Requires-Dist: trino~=0.331
Requires-Dist: dbt-core>=1.8.0
Dynamic: author
Dynamic: author-email
Dynamic: classifier
Dynamic: description
Dynamic: description-content-type
Dynamic: home-page
Dynamic: license
Dynamic: license-file
Dynamic: platform
Dynamic: requires-dist
Dynamic: requires-python
Dynamic: summary
